compython/__init__.py
compython/consts.py
compython/geometry_base.py
compython-2022.1.13.post18.dist-info/LICENSE
compython-2022.1.13.post18.dist-info/METADATA
compython-2022.1.13.post18.dist-info/WHEEL
compython-2022.1.13.post18.dist-info/top_level.txt
compython-2022.1.13.post18.dist-info/RECORD
