Metadata-Version: 2.1
Name: compython
Version: 2022.1.13.post18
Summary: compython
Home-page: https://github.com/sth-v/compython
Author: Andrew Astakhov
Author-email: aw.astakhov@gmail.com
License: UNKNOWN
Project-URL: Bug Tracker, https://github.com/sth-v/compython/issues
Platform: UNKNOWN
Classifier: Programming Language :: Python :: 3
Classifier: License :: OSI Approved :: MIT License
Classifier: Operating System :: OS Independent
Requires-Python: >=3.9
License-File: LICENSE
Requires-Dist: numpy (>=1.16.6)
Requires-Dist: scipy (>=1.7.1)
Requires-Dist: sklearn (>=1.0.1)
